Scapii/Scapii.py
Scapii/__init__.py
Scappi-1.0.0.dist-info/METADATA
Scappi-1.0.0.dist-info/WHEEL
Scappi-1.0.0.dist-info/top_level.txt
Scappi-1.0.0.dist-info/RECORD
