Metadata-Version: 2.1
Name: Scappi
Version: 1.0.0
Summary: Python to Scratch API Bridge
Home-page: https://github.com/kruffer/Scappi
Author: MrFluid
License: MIT
Platform: UNKNOWN
Classifier: Programming Language :: Python :: 3
Classifier: License :: OSI Approved :: MIT License
Classifier: Operating System :: OS Independent
Requires-Python: >=3.6
Requires-Dist: websocket-client
Requires-Dist: ScratchEncoder
Requires-Dist: requests
